AUTHORS
LICENSE
MANIFEST.in
NEWS
README
setup.py
src/HTSQL_ORACLE.egg-info/PKG-INFO
src/HTSQL_ORACLE.egg-info/SOURCES.txt
src/HTSQL_ORACLE.egg-info/dependency_links.txt
src/HTSQL_ORACLE.egg-info/entry_points.txt
src/HTSQL_ORACLE.egg-info/not-zip-safe
src/HTSQL_ORACLE.egg-info/requires.txt
src/HTSQL_ORACLE.egg-info/top_level.txt
src/htsql_oracle/__init__.py
src/htsql_oracle/core/__init__.py
src/htsql_oracle/core/connect.py
src/htsql_oracle/core/introspect.py
src/htsql_oracle/core/split_sql.py
src/htsql_oracle/core/tr/__init__.py
src/htsql_oracle/core/tr/compile.py
src/htsql_oracle/core/tr/dump.py
src/htsql_oracle/core/tr/lookup.py
src/htsql_oracle/core/tr/reduce.py
src/htsql_oracle/core/tr/rewrite.py
src/htsql_oracle/core/tr/signature.py