Metadata-Version: 1.0
Name: HTSQL-ORACLE
Version: 2.3.1
Summary: A Database Query Language (Oracle backend)
Home-page: http://htsql.org/
Author: Clark C. Evans and Kirill Simonov; Prometheus Research, LLC
Author-email: cce@clarkevans.com, xi@resolvent.net
License: Evaluation License
Keywords: sql relational database query language
Platform: Any
